{"cameraMode":{"drawMode":0,"name":"Shaded","section":"Shading Mode"},"sceneLighting":true,"audioPlay":false,"sceneViewState":{"m_AlwaysRefresh":false,"showFog":true,"showSkybox":true,"showFlares":true,"showImageEffects":true,"showParticleSystems":true,"showVisualEffectGraphs":true,"m_FxEnabled":true},"in2DMode":false,"pivot":{"x":112.65369415283203,"y":-33.19956970214844,"z":-15.196866989135743},"rotation":{"x":0.0963994562625885,"y":0.7616413831710815,"z":-0.11652082949876785,"w":0.6301103830337524},"size":68.25575256347656,"orthographic":false}